flask_helmet/__init__.py
flask_helmet/flask_helmet.py
flask_helmet-1.0.0.dist-info/LICENSE
flask_helmet-1.0.0.dist-info/METADATA
flask_helmet-1.0.0.dist-info/WHEEL
flask_helmet-1.0.0.dist-info/top_level.txt
flask_helmet-1.0.0.dist-info/RECORD
