Metadata-Version: 2.1
Name: flask-helmet
Version: 1.0.0
Summary: A Flask extension for adding security headers to HTTP responses
Home-page: https://github.com/dillibk777/flask-helmet
Author: Dilli Babu Kadati
Author-email: dillibabukadati777@gmail.com
License: MIT
Keywords: flask security headers helmet
Platform: UNKNOWN
Classifier: Programming Language :: Python :: 3
Classifier: License :: OSI Approved :: MIT License
Classifier: Operating System :: OS Independent
License-File: LICENSE
Requires-Dist: flask
